{"sylvain veilleux": "jwst observations of starbursts: cold clouds and plumes launching in the   m82 outflow", "naoki bessho": "earth's alfv\\'en wings driven by the april 2023 coronal mass ejection", "aparna bhattacharya": "keck and hubble observations show that moa-2008-blg-379lb is a   super-jupiter orbiting an m dwarf", "haoming liang": "earth's alfv\\'en wings driven by the april 2023 coronal mass ejection", "jonathan ng": "earth's alfv\\'en wings driven by the april 2023 coronal mass ejection", "jason shuster": "earth's alfv\\'en wings driven by the april 2023 coronal mass ejection", "harsha gurram": "earth's alfv\\'en wings driven by the april 2023 coronal mass ejection", "jialu li": "constraints on dark photon dark matter using data from ligo's and   virgo's third observing run", "rachel rice": "earth's alfv\\'en wings driven by the april 2023 coronal mass ejection", "aikaterini vandorou": "keck and hubble observations show that moa-2008-blg-379lb is a   super-jupiter orbiting an m dwarf", "jongwon park": "constraints on dark photon dark matter using data from ligo's and   virgo's third observing run"}