{"alberto bolatto": "disentangling the co-evolution of galaxies and supermassive black holes   with prima", "benedikt diemer": "dynamics-based halo model for large scale structure", "lori feaga": "infrared compositional measurements in comet c/2017 k2 (pan-starrs) at   heliocentric distances beyond 2.3 au", "ronald gamble": "the black hole explorer: motivation and vision", "veselin kostov": "the inflated, eccentric warm jupiter toi-4914 b orbiting a metal-poor   star, and the hot jupiters toi-2714 b and toi-2981 b", "zorawar wadiasingh": "extragalactic magnetar giant flare grb 231115a: insights from fermi/gbm   observations", "igor andreoni": "ztf sn ia dr2: overview", "jialu li": "grb 221009a: the b.o.a.t burst that shines in gamma rays", "calvin osinga": "dynamics-based halo model for large scale structure"}